<document xml:lang="fkv" id="no_id"><header><title>Alkukursi 9</title><genre code="facta"/><author><person firstname="Terje" lastname="Aaronsen" sex="m" born="" nationality=""/></author><translator><person firstname="Terje" lastname="Aaronsen" sex="m" born="1947" nationality="NO"/></translator><year>2007</year><wordcount>1001</wordcount><conversion_status type="standard"/><availability><free/></availability><submitter name="Sindre Reino Trosterud" email="sindre.reino.trosterud@gmail.com"/><multilingual><language xml:lang="nob"/><language xml:lang="fkv"/></multilingual><metadata><uncomplete/></metadata><version>XSLtemplate $Revision: 105844 $; file-specific xsl  Revision; common.xsl  $Revision$; </version></header>
<body>
<p type="title">Alkukursi (30 tiimaa) kainun kielelä.</p>
<list><p type="listitem">Rästin viimi kerralta.</p>
<p type="listitem" xml:lang="nob">Verbbøyning (II) i presens (nåtid)</p>
<p type="listitem" xml:lang="nob">Kasusendinger (II)</p>
</list><list><p type="listitem">Pikku lukuteksti</p>
<p type="listitem">Minun ensi kehtolaulu</p>
<p type="listitem">Sanalista 9</p>
</list><p type="title">1. Rästin viimi kerralta.</p>
<p type="title" xml:lang="nob">2. Verbbøyning (II) i presens (nåtid)</p>
<list><p type="listitem" xml:lang="nob">puhhuut (= å snakke)</p>
</list><p xml:lang="nob">Entall</p>
<p xml:lang="nob">Flertall</p>
<p>1. pers mie puhun</p>
<p>2. pers sie puhut</p>
<p>3. pers hän puhhuu</p>
<p>1. pers met puhuma</p>
<p>2. pers tet puhutta</p>
<p>3. pers het puhuthaan</p>
<p xml:lang="nob"/>
<p xml:lang="nob"/>
<p><span type="quote">Mie puhun kainun kieltä Mie en puhu ...</span></p>
<p><span type="quote">Sie puhut kans rui(j/ð)aa Sie et puhu...</span></p>
<p><span type="quote">Hän puhhuu tyhä /rui(j/ð)aa Hän ei puhu ...</span></p>
<p xml:lang="nob"/>
<p><span type="quote">Met puhuma kielestä Met emmä puhu ...</span></p>
<p><span type="quote">Tet puhutta saamenkieltä Tet että puhu ...</span></p>
<p><span type="quote">Het puhuthaan aamusta ilthaan Het ei puhu ...</span></p>
<p xml:lang="nob"/>
<p><span type="quote">Puhu hithaammasti! Älä puhu ...</span></p>
<p><span type="quote">Puhukkaa selvästi! Älkkää puhukkaa ... </span></p>
<p xml:lang="nob"/>
<p xml:lang="nob"/>
<list><p type="listitem" xml:lang="nob">assuut (= å bo)</p>
</list><p xml:lang="nob">Entall</p>
<p xml:lang="nob">Flertall</p>
<p>1. pers mie asun</p>
<p>2. pers sie asut</p>
<p>3, pers hän assuu</p>
<p>1. pers met asuma</p>
<p>2. pers tet asutta</p>
<p>3. pers het asuthaan</p>
<p xml:lang="nob"/>
<p xml:lang="nob"/>
<p><span type="quote">Mie asun Raisissa/</span></p>
<p><span type="quote">Pyssyjovessa Mie en asu ...</span></p>
<p><span type="quote">Sie asut kotona Sie et asu ...</span></p>
<p><span type="quote">Hän assuu perheen kansa </span></p>
<p><span type="quote">pienessä talossa Hän ei asu ...</span></p>
<p xml:lang="nob"/>
<p><span type="quote">Met asuma Tromssassa Met emmä asu ...</span></p>
<p><span type="quote">Tet asutta koko kesän ulkomaala Tet että asu ...</span></p>
<p><span type="quote">Het asuthaan Ruottissa Het ei asu ...</span></p>
<p xml:lang="nob"/>
<p><span type="quote">Asu siinä! Älä asu ...</span></p>
<p><span type="quote">Asukkaa siinä Älkkää asukkaa ---</span></p>
<p xml:lang="nob"/>
<p xml:lang="nob"/>
<list><p type="listitem" xml:lang="nob">syö(ð)ä (= å spise) (Jf. juo(ð)a)</p>
</list><p xml:lang="nob">Entall</p>
<p xml:lang="nob">Flertall</p>
<p>1. pers mie syön</p>
<p>2. pers sie syöt</p>
<p>3, pers hän syöpi</p>
<p>1. pers met syömä</p>
<p>2. pers tet syöttä</p>
<p>3. pers het syö(ð)hään</p>
<p xml:lang="nob"/>
<p xml:lang="nob"/>
<p><span type="quote">Mie syön leippää Mie en ...</span></p>
<p><span type="quote">Sie syöt murkinaa Sie ...</span></p>
<p><span type="quote">Hän syöpi liian paljon Hän ...</span></p>
<p xml:lang="nob"/>
<p><span type="quote">Met syömä lämmintä ruokkaa Met ...</span></p>
<p><span type="quote">Tet syöttä kylmää kallaa Tet ...</span></p>
<p><span type="quote">Het syö(ð)hään neljen aikana Het ...</span></p>
<p xml:lang="nob"/>
<p><span type="quote">Syö nyt! Ä...</span></p>
<p><span type="quote">Syökkää ruvan! Ä...</span></p>
<p xml:lang="nob"/>
<p type="title" xml:lang="nob">3. Kasusendinger (II)</p>
<list><p type="listitem" xml:lang="nob"><span>–t (flertall) Akkusativ </span></p>
</list><p><span type="quote">Kaikki pojat oon täälä</span></p>
<p><span type="quote">Tyttäret tulhaan kaupasta </span></p>
<p><span type="quote">Hän osti uu(ð)et sivakat (uusi:uu(ð)e-)</span></p>
<list><p type="listitem" xml:lang="nob">–na/-nä ( angir som oftest tidspunkt) Essiv</p>
</list><p><span type="quote">Mie tulen pyhänä</span></p>
<p><span type="quote">Suomalaiset tulhaan keskiviikkona</span></p>
<p><span type="quote">Hän tullee vii(ð)en kuu(ð)en aikana</span></p>
<p xml:lang="nob"/>
<p type="title">4. Pikku lukuteksti</p>
<p>Jussa: Hyvvää päivää!</p>
<p>Leena: Päivää! Kuka sie olet?</p>
<p>Jussa: Mie olen Jussa. Mutta kukapa sie olet?</p>
<p>Leena: Mie olen Leena. Jussa mistä sie olet?</p>
<p>Jussa: Mie olen Raisista. Mistäpä sie olet Leena?</p>
<p><span type="quote">Leena: Mie olen Pyssyjovesta. Mie olen Pyssyjoven kaunis tytär. Kunka
se mennee, Jussa?</span></p>
<p>Jussa: Kiitoksii paljon, se mennee hyvin.</p>
<p>Leena: Hyvästi, Jussa, ja näkemiin!</p>
<p>Jussa: Hyvästi, Leena, Pyssyjoven kaunis tytär.</p>
<p>Ja näkemiin. Toivottaavasti!</p>
<p type="title">5. Minun ensi kehtolaulu</p>
<p><span type="quote">Ensi laulu minkä kuulla sain,</span></p>
<p><span type="quote">Oli mamman kehtolaulu.</span></p>
<p><span type="quote">Sanat pehmeiset meni syðämheen,</span></p>
<p><span type="quote">Ja itku siiheen loppui.</span></p>
<p xml:lang="nob"/>
<p><span type="quote">Net lullathiin minun pehmeesti,</span></p>
<p><span type="quote">Niin rauhalisesti unheen.</span></p>
<p><span type="quote">Tien sievän mulle näytethiin</span></p>
<p><span type="quote">Sinne meiðän pienheen talhoon.</span></p>
<p xml:lang="nob"/>
<p><span type="quote">Tie muistuu mulle vielä nyt</span></p>
<p><span type="quote">Ko silmät kiini panen.</span></p>
<p><span type="quote">Siinä enkeli seissoo naurain</span></p>
<p><span type="quote">Niin kaunihiisti mulle.</span></p>
<p xml:lang="nob"/>
<p><span type="quote">Ko väsynheenä illalla</span></p>
<p><span type="quote">Panen maata rauhalisesti,</span></p>
<p><span type="quote">Kuuluu kuiskaus mamman hauðasta;</span></p>
<p><span type="quote">Minun ensi kehtolaulu.</span></p>
<p xml:lang="nob"/>
<p xml:lang="nob"><span type="quote" xml:lang="nob">Nuotti: Lars Søraas Sanat: Terje Aronsen</span></p>
<p xml:lang="nob"/>
<p type="title">6. Sanalista 9</p>
<p xml:lang="nob"/>
<p>puhhuut:puhu-</p>
<p xml:lang="nob">rui(j/ð)a</p>
<p>Rui(j/ð)a</p>
<p>saamenkieli:s.kiele-:s.kieltä</p>
<p>hi(ð)as:hithaa-</p>
<p>selvä</p>
<p>assuut:asu-</p>
<p>kotona</p>
<p>Tromssa</p>
<p>kesä</p>
<p>ulkomaa</p>
<p>Ruotti</p>
<p>syö(ð)ä:syö-:syöpi</p>
<p>leipä:leivä-:leippää</p>
<p>murkina (ruoka)</p>
<p>liian</p>
<p>ruoka:ruva-:ruokkaa</p>
<p>kala</p>
<p>sivakka:sivaka-</p>
<p>suomalainen:s.laise-:s.laista</p>
<p>kaunis:kaunhii-</p>
<p>toivottaavasti</p>
<p>minkä (relativ pron.)</p>
<p>kuulla:kuule-:kuulee</p>
<p>saa(’/ð)a/saa’a:saa-:saapi</p>
<p>pehmeinen:pehmeise-:pehmeistä</p>
<p>itku</p>
<p>loppuut:lopu-</p>
<p>lullata:lullaa-</p>
<p>rauhalinen:rauhalise-:rauhalista</p>
<p xml:lang="nob">uni:une-:unta</p>
<p>tie</p>
<p>sievä</p>
<p>näyttäät:näytä-</p>
<p>muistuut</p>
<p>kiini</p>
<p>naurain</p>
<p>väsyny:väsynhee-</p>
<p>panna maata</p>
<p>kuiskaus:kuiskaukse-</p>
<p>hauta:hau(ð)a-:hauttaa</p>
<p xml:lang="nob">å snakke</p>
<p xml:lang="nob">norsk</p>
<p xml:lang="nob">Norge</p>
<p xml:lang="nob">samisk</p>
<p xml:lang="nob">sakte</p>
<p xml:lang="nob">tydelig, klar -t</p>
<p xml:lang="nob">å bo</p>
<p xml:lang="nob">hjemme</p>
<p xml:lang="nob">Tromsø</p>
<p xml:lang="nob">sommer –en</p>
<p xml:lang="nob">utland -et</p>
<p xml:lang="nob">Sverige</p>
<p xml:lang="nob">å spise</p>
<p xml:lang="nob">brød –et</p>
<p xml:lang="nob">middag -en</p>
<p xml:lang="nob">altfor, for</p>
<p xml:lang="nob">mat -en</p>
<p xml:lang="nob">fisk –en</p>
<p xml:lang="nob">ski -en</p>
<p xml:lang="nob">finlender –en, finne –n</p>
<p xml:lang="nob">vak|ker –re, pen -e</p>
<p xml:lang="nob">forhåpentligvis</p>
<p xml:lang="nob">som</p>
<p xml:lang="nob">å høre</p>
<p xml:lang="nob">å få</p>
<p xml:lang="nob">myk –t</p>
<p xml:lang="nob">gråt -en</p>
<p xml:lang="nob">å slutte</p>
<p xml:lang="nob">å lulle</p>
<p xml:lang="nob">rolig, fredfull –t</p>
<p xml:lang="nob">søvn –en, drøm -men</p>
<p xml:lang="nob">vei –en</p>
<p xml:lang="nob">nydelig, skjønn</p>
<p xml:lang="nob">å vise</p>
<p xml:lang="nob">huskes</p>
<p xml:lang="nob">igjen</p>
<p xml:lang="nob">smilende</p>
<p xml:lang="nob">trøtt</p>
<p xml:lang="nob">å legge seg</p>
<p xml:lang="nob">visking –a</p>
<p xml:lang="nob">grav -a</p>
<p xml:lang="nob"/>
<p xml:lang="nob"/>
<p xml:lang="nob"/>
<p type="title" xml:lang="nob">2. Verbbøyning (II) i presens (nåtid)</p>
<p xml:lang="nob">puhhuut (= å snakke)</p>
<p xml:lang="nob">Entall</p>
<p xml:lang="nob">Flertall</p>
<p>1. pers mie puhun</p>
<p>2. pers sie puhut</p>
<p>3. pers hän puhhuu</p>
<p>1. pers met puhuma</p>
<p>2. pers tet puhutta</p>
<p>3. pers het puhuthaan</p>
<p xml:lang="nob"/>
<p xml:lang="nob"/>
<p><span type="quote">Mie puhun kainun kieltä Mie en puhu ...</span></p>
<p><span type="quote">Sie puhut kans rui(j/ð)aa Sie et puhu... </span></p>
<p><span type="quote">Hän puhhuu tyhä rui(j/ð)aa Hän ei puhu ...</span></p>
<p xml:lang="nob"/>
<p><span type="quote">Met puhuma kielestä Met emmä puhu ...</span></p>
<p xml:lang="nob"/>
<p><span type="quote">Tet puhutta saamen kieltä Tet että puhu ...</span></p>
<p xml:lang="nob"/>
<p><span type="quote">Het puhuthaan </span></p>
<p><span type="quote">aamusta ilthaan Het ei puhu ...</span></p>
<p xml:lang="nob"/>
<p><span type="quote">Puhu hithaammasti! Älä puhu ...</span></p>
<p><span type="quote">Puhukkaa selvästi! Älkkää puhukkaa .</span></p>
<p xml:lang="nob"/>
<p xml:lang="nob"/>
<p xml:lang="nob"/>
<p xml:lang="nob"/>
<p xml:lang="nob"/>
<p xml:lang="nob"/>
<p xml:lang="nob"/>
<p xml:lang="nob">assuut (= å bo)</p>
<p xml:lang="nob">Entall</p>
<p xml:lang="nob">Flertall</p>
<p>1. pers mie asun</p>
<p>2. pers sie asut</p>
<p>3, pers hän assuu</p>
<p>1. pers met asuma</p>
<p>2. pers tet asutta</p>
<p>3. pers het asuthaan</p>
<p xml:lang="nob"/>
<p xml:lang="nob"/>
<p><span type="quote">Mie asun Raisissa/</span></p>
<p><span type="quote">Pyssyjovessa Mie en asu ...</span></p>
<p><span type="quote">Sie asut kotona Sie et asu ...</span></p>
<p><span type="quote">Hän assuu perheen kansa </span></p>
<p><span type="quote">pienessä talossa Hän ei asu ...</span></p>
<p xml:lang="nob"/>
<p><span type="quote">Met asuma Tromssassa Met emmä asu ...</span></p>
<p><span type="quote">Tet asutta koko kesän </span></p>
<p><span type="quote">ulkomaala Tet että asu ...</span></p>
<p><span type="quote">Het asuthaan Ruottissa Het ei asu ...</span></p>
<p xml:lang="nob"/>
<p><span type="quote">Asu siinä! Älä asu ... </span></p>
<p><span type="quote">Asukkaa siinä Älkkää asukkaa...</span></p>
<p xml:lang="nob"/>
<p xml:lang="nob"/>
<p xml:lang="nob"/>
<p xml:lang="nob"/>
<p xml:lang="nob"/>
<p xml:lang="nob"/>
<p xml:lang="nob"/>
<p xml:lang="nob"/>
<p xml:lang="nob"/>
<p xml:lang="nob"/>
<p xml:lang="nob">syö(ð)ä (= å spise) (Jf. juo(ð)a)</p>
<p xml:lang="nob">Entall</p>
<p xml:lang="nob">Flertall</p>
<p>1. pers mie syön</p>
<p>2. pers sie syöt</p>
<p>3, pers hän syöpi</p>
<p>1. pers met syömä</p>
<p>2. pers tet syöttä</p>
<p>3. pers het syö(ð)hään</p>
<p xml:lang="nob"/>
<p xml:lang="nob"/>
<p><span type="quote">Mie syön leippää Mie en ...</span></p>
<p><span type="quote">Sie syöt murkinaa Sie ...</span></p>
<p><span type="quote">Hän syöpi liian paljon Hän ...</span></p>
<p xml:lang="nob"/>
<p><span type="quote">Met syömä lämmintä Met ...</span></p>
<p><span type="quote">ruokkaa</span></p>
<p><span type="quote">Tet syöttä kylmää kallaa Tet ...</span></p>
<p><span type="quote">Het syö(ð)hään neljen</span></p>
<p><span type="quote">aikana Het ...</span></p>
<p xml:lang="nob"/>
<p><span type="quote">Syö nyt! Ä...</span></p>
<p><span type="quote">Syökkää ruvan! Ä...</span></p>
<p type="title" xml:lang="nob">3. Kasusendinger (II)</p>
<p type="title" xml:lang="nob">–t (flertall) Akkusativ</p>
<p><span type="quote">Kaikki pojat oon täälä</span></p>
<p><span type="quote">Tyttäret tulhaan kaupasta </span></p>
<p><span type="quote">Hän osti uu(ð)et sivakat (uusi:uu(ð)e-)</span></p>
<p xml:lang="nob"><span type="quote" xml:lang="nob">–na/-nä (angir som oftest tids(punkt)) Essiv</span></p>
<p><span type="quote">Mie tulen pyhänä</span></p>
<p><span type="quote">Suomalaiset tulhaan keskiviikkona</span></p>
<p><span type="quote">Hän tullee vii(ð)en kuu(ð)en aikana</span></p>
<p xml:lang="nob"/>
<p xml:lang="nob"/>
<p xml:lang="nob"/>
<p xml:lang="nob"/>
<p xml:lang="nob"/>
<p xml:lang="nob"/>
<p type="title">Minun ensi kehtolaulu</p>
<p><span type="quote">Ensi laulu minkä kuulla sain,</span></p>
<p><span type="quote">Oli mamman kehtolaulu.</span></p>
<p><span type="quote">Sanat pehmeiset meni syðämheen,</span></p>
<p><span type="quote">Ja itku siiheen loppui.</span></p>
<p xml:lang="nob"/>
<p><span type="quote">Net lullathiin minun pehmeesti,</span></p>
<p><span type="quote">Niin rauhalisesti unheen.</span></p>
<p><span type="quote">Tien sievän mulle näytethiin</span></p>
<p><span type="quote">Sinne meiðän pienheen talhoon.</span></p>
<p xml:lang="nob"/>
<p><span type="quote">Tie muistuu mulle vielä nyt</span></p>
<p><span type="quote">Ko silmät kiini panen.</span></p>
<p><span type="quote">Siinä enkeli seissoo naurain</span></p>
<p><span type="quote">Niin kaunihiisti mulle.</span></p>
<p xml:lang="nob"/>
<p><span type="quote">Ko väsynheenä illalla</span></p>
<p><span type="quote">Panen maata rauhalisesti,</span></p>
<p><span type="quote">Kuuluu kuiskaus mamman hauðasta;</span></p>
<p><span type="quote">Minun ensi kehtolaulu.</span></p>
<p xml:lang="nob"/>
<p xml:lang="nob"><span type="quote" xml:lang="nob">Nuotti: Lars Søraas Sanat: Terje Aronsen</span></p>
<p xml:lang="nob"/>
<p xml:lang="nob"/>
<p xml:lang="nob"/>
<p xml:lang="nob"/>
<p xml:lang="nob"/>
<p xml:lang="nob"/>
<p xml:lang="nob"/>
<p xml:lang="nob"/>
<p xml:lang="nob"/>
<p xml:lang="nob"/>
<p xml:lang="nob"/>
<p xml:lang="nob"/>
<p xml:lang="nob"/>
<p type="title">Pikku lukuteksti</p>
<p>Jussa: Hyvvää päivää!</p>
<p>Leena: Päivää! Kuka sie olet?</p>
<p><span type="quote">Jussa: Mie olen Jussa. Mutta kukapa sie olet?</span></p>
<p>Leena: Mie olen Leena. Jussa mistä sie olet?</p>
<p><span type="quote">Jussa: Mie olen Raisista. Mistäpä sie olet Leena?</span></p>
<p><span type="quote">Leena: Mie olen Pyssyjovesta. Mie olen Pyssyjoven kaunis tytär. Kunka
se mennee, Jussa?</span></p>
<p>Jussa: Kiitoksii paljon, se mennee hyvin.</p>
<p>Leena: Hyvästi, Jussa, ja näkemiin!</p>
<p><span type="quote">Jussa: Hyvästi, Leena, Pyssyjoven kaunis tytär.</span></p>
<p>Ja näkemiin. Toivottaavasti!</p>
<p xml:lang="nob"/>
<p xml:lang="nob"/>
<p xml:lang="nob"/>
</body></document>
